{
  "Africa": {
    "2019": {
      "adpe": 8.92514e-8,
      "ap": 0.0000329446,
      "ctue": 0.00944391,
      "ctuh-c": 1.88351e-10,
      "ctuh-nc": 6.50743e-10,
      "gwp": 0.00417466,
      "ir": 0.000371456,
      "pm": 5.70408e-7,
      "wu": 0.00135372
    },
    "2020": {
      "adpe": 9.55786e-8,
      "ap": 0.0000348782,
      "ctue": 0.00992911,
      "ctuh-c": 1.91815e-10,
      "ctuh-nc": 6.88659e-10,
      "gwp": 0.00441587,
      "ir": 0.000395119,
      "pm": 6.02378e-7,
      "wu": 0.0014308
    },
    "2021": {
      "adpe": 9.90171e-8,
      "ap": 0.0000349562,
      "ctue": 0.00997529,
      "ctuh-c": 1.97139e-10,
      "ctuh-nc": 6.93923e-10,
      "gwp": 0.00442487,
      "ir": 0.000399341,
      "pm": 6.00528e-7,
      "wu": 0.00144506
    },
    "2022": {
      "adpe": 1.03663e-7,
      "ap": 0.0000352525,
      "ctue": 0.0100679,
      "ctuh-c": 2.01865e-10,
      "ctuh-nc": 7.03848e-10,
      "gwp": 0.0044612,
      "ir": 0.00040696,
      "pm": 6.01561e-7,
      "wu": 0.00146854
    },
    "2023": {
      "adpe": 1.11387e-7,
      "ap": 0.00003576,
      "ctue": 0.0102486,
      "ctuh-c": 2.10761e-10,
      "ctuh-nc": 7.21356e-10,
      "gwp": 0.00452926,
      "ir": 0.000420119,
      "pm": 6.0273e-7,
      "wu": 0.00150864
    },
    "2024": {
      "adpe": 1.12838e-7,
      "ap": 0.0000357083,
      "ctue": 0.0102297,
      "ctuh-c": 2.09331e-10,
      "ctuh-nc": 7.22145e-10,
      "gwp": 0.00452602,
      "ir": 0.00042189,
      "pm": 5.99234e-7,
      "wu": 0.00150953
    }
  },
  "Asia": {
    "2019": {
      "adpe": 1.22222e-7,
      "ap": 0.0000383871,
      "ctue": 0.00558938,
      "ctuh-c": 2.13498e-10,
      "ctuh-nc": 5.57951e-10,
      "gwp": 0.00289098,
      "ir": 0.000290965,
      "pm": 9.74566e-7,
      "wu": 0.00165253
    },
    "2020": {
      "adpe": 1.36882e-7,
      "ap": 0.0000411372,
      "ctue": 0.00594047,
      "ctuh-c": 2.33856e-10,
      "ctuh-nc": 6.01609e-10,
      "gwp": 0.00307248,
      "ir": 0.000316352,
      "pm": 0.00000104214,
      "wu": 0.00178899
    },
    "2021": {
      "adpe": 1.57744e-7,
      "ap": 0.0000444383,
      "ctue": 0.00649119,
      "ctuh-c": 2.80762e-10,
      "ctuh-nc": 6.59004e-10,
      "gwp": 0.00328081,
      "ir": 0.000347537,
      "pm": 0.00000112341,
      "wu": 0.0019758
    },
    "2022": {
      "adpe": 1.84488e-7,
      "ap": 0.0000476269,
      "ctue": 0.00706804,
      "ctuh-c": 3.15694e-10,
      "ctuh-nc": 7.25472e-10,
      "gwp": 0.00353414,
      "ir": 0.000391254,
      "pm": 0.00000118404,
      "wu": 0.0021643
    },
    "2023": {
      "adpe": 2.15728e-7,
      "ap": 0.0000497821,
      "ctue": 0.00758076,
      "ctuh-c": 3.53235e-10,
      "ctuh-nc": 7.87683e-10,
      "gwp": 0.00372747,
      "ir": 0.000437252,
      "pm": 0.00000120697,
      "wu": 0.00233234
    },
    "2024": {
      "adpe": 2.56322e-7,
      "ap": 0.0000513541,
      "ctue": 0.00837341,
      "ctuh-c": 3.85752e-10,
      "ctuh-nc": 8.69194e-10,
      "gwp": 0.00402941,
      "ir": 0.000505525,
      "pm": 0.00000117568,
      "wu": 0.0024984
    }
  },
  "Europe": {
    "2019": {
      "adpe": 2.07896e-7,
      "ap": 0.0000732482,
      "ctue": 0.0123246,
      "ctuh-c": 6.35793e-10,
      "ctuh-nc": 1.06415e-9,
      "gwp": 0.00548342,
      "ir": 0.000496016,
      "pm": 0.00000192086,
      "wu": 0.00324498
    },
    "2020": {
      "adpe": 2.44284e-7,
      "ap": 0.0000786716,
      "ctue": 0.0138522,
      "ctuh-c": 7.30797e-10,
      "ctuh-nc": 1.18315e-9,
      "gwp": 0.00601037,
      "ir": 0.000563283,
      "pm": 0.00000202268,
      "wu": 0.00356564
    },
    "2021": {
      "adpe": 2.53012e-7,
      "ap": 0.0000805188,
      "ctue": 0.013467,
      "ctuh-c": 7.07002e-10,
      "ctuh-nc": 1.19239e-9,
      "gwp": 0.00600247,
      "ir": 0.000572276,
      "pm": 0.00000208717,
      "wu": 0.00363195
    },
    "2022": {
      "adpe": 3.04206e-7,
      "ap": 0.0000830717,
      "ctue": 0.0145961,
      "ctuh-c": 7.95938e-10,
      "ctuh-nc": 1.29547e-9,
      "gwp": 0.00631974,
      "ir": 0.000646607,
      "pm": 0.00000208726,
      "wu": 0.00389327
    },
    "2023": {
      "adpe": 3.5352e-7,
      "ap": 0.0000823968,
      "ctue": 0.0162883,
      "ctuh-c": 8.9552e-10,
      "ctuh-nc": 1.3983e-9,
      "gwp": 0.00670878,
      "ir": 0.000729905,
      "pm": 0.00000194537,
      "wu": 0.00404932
    },
    "2024": {
      "adpe": 4.66471e-7,
      "ap": 0.0000898014,
      "ctue": 0.0178751,
      "ctuh-c": 9.34295e-10,
      "ctuh-nc": 1.62702e-9,
      "gwp": 0.0075596,
      "ir": 0.000920444,
      "pm": 0.00000197598,
      "wu": 0.00457677
    }
  },
  "North America": {
    "2019": {
      "adpe": 1.9385e-7,
      "ap": 0.000072753,
      "ctue": 0.0101249,
      "ctuh-c": 5.34752e-10,
      "ctuh-nc": 9.73183e-10,
      "gwp": 0.00491012,
      "ir": 0.000443095,
      "pm": 0.00000200281,
      "wu": 0.00313767
    },
    "2020": {
      "adpe": 2.2827e-7,
      "ap": 0.0000744931,
      "ctue": 0.0112369,
      "ctuh-c": 6.08629e-10,
      "ctuh-nc": 1.05461e-9,
      "gwp": 0.00521691,
      "ir": 0.00049927,
      "pm": 0.00000198965,
      "wu": 0.00332186
    },
    "2021": {
      "adpe": 2.60315e-7,
      "ap": 0.0000750029,
      "ctue": 0.0118306,
      "ctuh-c": 6.55573e-10,
      "ctuh-nc": 1.10952e-9,
      "gwp": 0.00536145,
      "ir": 0.000544427,
      "pm": 0.0000019529,
      "wu": 0.00344466
    },
    "2022": {
      "adpe": 2.93958e-7,
      "ap": 0.0000743918,
      "ctue": 0.0127198,
      "ctuh-c": 7.15865e-10,
      "ctuh-nc": 1.16925e-9,
      "gwp": 0.00554423,
      "ir": 0.000595501,
      "pm": 0.00000186296,
      "wu": 0.00354253
    },
    "2023": {
      "adpe": 3.24319e-7,
      "ap": 0.0000746357,
      "ctue": 0.0128874,
      "ctuh-c": 7.24863e-10,
      "ctuh-nc": 1.20991e-9,
      "gwp": 0.00562324,
      "ir": 0.000637864,
      "pm": 0.00000182412,
      "wu": 0.00362838
    },
    "2024": {
      "adpe": 3.83722e-7,
      "ap": 0.0000750191,
      "ctue": 0.0134823,
      "ctuh-c": 7.52277e-10,
      "ctuh-nc": 1.29811e-9,
      "gwp": 0.00584715,
      "ir": 0.00072564,
      "pm": 0.00000173366,
      "wu": 0.00379855
    }
  },
  "Oceania": {
    "2019": {
      "adpe": 3.31615e-7,
      "ap": 0.0000326288,
      "ctue": 0.0118795,
      "ctuh-c": 5.51044e-10,
      "ctuh-nc": 9.55573e-10,
      "gwp": 0.00434736,
      "ir": 0.000643584,
      "pm": 2.76163e-7,
      "wu": 0.00216631
    },
    "2020": {
      "adpe": 3.99103e-7,
      "ap": 0.0000358856,
      "ctue": 0.0132965,
      "ctuh-c": 6.36928e-10,
      "ctuh-nc": 1.09341e-9,
      "gwp": 0.00482082,
      "ir": 0.000749885,
      "pm": 2.5903e-7,
      "wu": 0.00248534
    },
    "2021": {
      "adpe": 4.85486e-7,
      "ap": 0.0000407159,
      "ctue": 0.0151581,
      "ctuh-c": 7.4325e-10,
      "ctuh-nc": 1.2764e-9,
      "gwp": 0.00547614,
      "ir": 0.000889144,
      "pm": 2.5572e-7,
      "wu": 0.00291224
    },
    "2022": {
      "adpe": 5.57932e-7,
      "ap": 0.0000445575,
      "ctue": 0.0167632,
      "ctuh-c": 8.31748e-10,
      "ctuh-nc": 1.43052e-9,
      "gwp": 0.00603696,
      "ir": 0.00100737,
      "pm": 2.42334e-7,
      "wu": 0.00326271
    },
    "2023": {
      "adpe": 6.66012e-7,
      "ap": 0.0000507732,
      "ctue": 0.0184,
      "ctuh-c": 9.15559e-10,
      "ctuh-nc": 1.6408e-9,
      "gwp": 0.00673942,
      "ir": 0.00117691,
      "pm": 2.59675e-7,
      "wu": 0.00377182
    },
    "2024": {
      "adpe": 6.3632e-7,
      "ap": 0.0000488075,
      "ctue": 0.0176268,
      "ctuh-c": 9.00883e-10,
      "ctuh-nc": 1.56677e-9,
      "gwp": 0.00639518,
      "ir": 0.00111728,
      "pm": 2.70658e-7,
      "wu": 0.0036317
    }
  },
  "South America": {
    "2019": {
      "adpe": 1.04101e-7,
      "ap": 0.0000474315,
      "ctue": 0.0201957,
      "ctuh-c": 4.56498e-10,
      "ctuh-nc": 1.14726e-9,
      "gwp": 0.00792885,
      "ir": 0.00064458,
      "pm": 5.47762e-7,
      "wu": 0.0019794
    },
    "2020": {
      "adpe": 1.21833e-7,
      "ap": 0.0000496655,
      "ctue": 0.0205256,
      "ctuh-c": 4.85026e-10,
      "ctuh-nc": 1.18895e-9,
      "gwp": 0.00806663,
      "ir": 0.000670206,
      "pm": 5.98588e-7,
      "wu": 0.00211245
    },
    "2021": {
      "adpe": 1.47792e-7,
      "ap": 0.0000477901,
      "ctue": 0.0206015,
      "ctuh-c": 5.39761e-10,
      "ctuh-nc": 1.20019e-9,
      "gwp": 0.00791266,
      "ir": 0.000686865,
      "pm": 5.21824e-7,
      "wu": 0.00215236
    },
    "2022": {
      "adpe": 1.94677e-7,
      "ap": 0.0000509592,
      "ctue": 0.0221975,
      "ctuh-c": 6.0234e-10,
      "ctuh-nc": 1.32592e-9,
      "gwp": 0.00849046,
      "ir": 0.000779371,
      "pm": 5.05744e-7,
      "wu": 0.00240142
    },
    "2023": {
      "adpe": 2.54208e-7,
      "ap": 0.0000548818,
      "ctue": 0.0231922,
      "ctuh-c": 6.6904e-10,
      "ctuh-nc": 1.44494e-9,
      "gwp": 0.00887255,
      "ir": 0.000869074,
      "pm": 5.38982e-7,
      "wu": 0.00271208
    },
    "2024": {
      "adpe": 2.99391e-7,
      "ap": 0.000057902,
      "ctue": 0.0237452,
      "ctuh-c": 7.10295e-10,
      "ctuh-nc": 1.5289e-9,
      "gwp": 0.00911446,
      "ir": 0.000934093,
      "pm": 5.73057e-7,
      "wu": 0.0029439
    }
  }
}