{
  "Africa": {
    "2019": {
      "adpe": 8.15926e-8,
      "ap": 0.0000326339,
      "ctue": 0.00947511,
      "ctuh-c": 1.93308e-10,
      "ctuh-nc": 6.4073e-10,
      "gwp": 0.00415414,
      "ir": 0.000360417,
      "pm": 5.70805e-7,
      "wu": 0.00132866
    },
    "2020": {
      "adpe": 8.95619e-8,
      "ap": 0.0000346526,
      "ctue": 0.00999608,
      "ctuh-c": 1.99368e-10,
      "ctuh-nc": 6.81999e-10,
      "gwp": 0.00440617,
      "ir": 0.00038654,
      "pm": 6.02777e-7,
      "wu": 0.00141405
    },
    "2021": {
      "adpe": 9.18066e-8,
      "ap": 0.0000346712,
      "ctue": 0.0100358,
      "ctuh-c": 2.04995e-10,
      "ctuh-nc": 6.85258e-10,
      "gwp": 0.0044087,
      "ir": 0.000388843,
      "pm": 6.01034e-7,
      "wu": 0.00142378
    },
    "2022": {
      "adpe": 9.61216e-8,
      "ap": 0.0000350164,
      "ctue": 0.0101371,
      "ctuh-c": 2.10493e-10,
      "ctuh-nc": 6.95326e-10,
      "gwp": 0.00444741,
      "ir": 0.00039607,
      "pm": 6.04173e-7,
      "wu": 0.00144856
    },
    "2023": {
      "adpe": 1.04498e-7,
      "ap": 0.0000353901,
      "ctue": 0.0102758,
      "ctuh-c": 2.18323e-10,
      "ctuh-nc": 7.11227e-10,
      "gwp": 0.00449908,
      "ir": 0.000409045,
      "pm": 6.01672e-7,
      "wu": 0.00148539
    },
    "2024": {
      "adpe": 1.08945e-7,
      "ap": 0.0000353673,
      "ctue": 0.0102939,
      "ctuh-c": 2.23204e-10,
      "ctuh-nc": 7.15941e-10,
      "gwp": 0.00449664,
      "ir": 0.0004138,
      "pm": 5.96322e-7,
      "wu": 0.00149865
    },
    "2025": {
      "adpe": 1.14859e-7,
      "ap": 0.0000355052,
      "ctue": 0.0102987,
      "ctuh-c": 2.24092e-10,
      "ctuh-nc": 7.23415e-10,
      "gwp": 0.00450702,
      "ir": 0.000421549,
      "pm": 5.93238e-7,
      "wu": 0.00151787
    }
  },
  "Asia": {
    "2019": {
      "adpe": 1.23654e-7,
      "ap": 0.0000411272,
      "ctue": 0.00549695,
      "ctuh-c": 2.26675e-10,
      "ctuh-nc": 5.69873e-10,
      "gwp": 0.00291259,
      "ir": 0.00028758,
      "pm": 0.00000108383,
      "wu": 0.00175483
    },
    "2020": {
      "adpe": 1.40498e-7,
      "ap": 0.0000442129,
      "ctue": 0.00590239,
      "ctuh-c": 2.49949e-10,
      "ctuh-nc": 6.19695e-10,
      "gwp": 0.00311977,
      "ir": 0.000316797,
      "pm": 0.00000115863,
      "wu": 0.00190911
    },
    "2021": {
      "adpe": 1.64197e-7,
      "ap": 0.0000479225,
      "ctue": 0.00653481,
      "ctuh-c": 3.02896e-10,
      "ctuh-nc": 6.84991e-10,
      "gwp": 0.00335855,
      "ir": 0.000352517,
      "pm": 0.00000124889,
      "wu": 0.00211973
    },
    "2022": {
      "adpe": 1.94539e-7,
      "ap": 0.0000514864,
      "ctue": 0.00718984,
      "ctuh-c": 3.42132e-10,
      "ctuh-nc": 7.60172e-10,
      "gwp": 0.00364547,
      "ir": 0.000402226,
      "pm": 0.00000131549,
      "wu": 0.00233156
    },
    "2023": {
      "adpe": 2.29767e-7,
      "ap": 0.0000538335,
      "ctue": 0.00776804,
      "ctuh-c": 3.84085e-10,
      "ctuh-nc": 8.29895e-10,
      "gwp": 0.0038618,
      "ir": 0.000454165,
      "pm": 0.00000133815,
      "wu": 0.00251809
    },
    "2024": {
      "adpe": 2.83145e-7,
      "ap": 0.0000562095,
      "ctue": 0.00871331,
      "ctuh-c": 4.2756e-10,
      "ctuh-nc": 9.34828e-10,
      "gwp": 0.00423104,
      "ir": 0.000540919,
      "pm": 0.00000131453,
      "wu": 0.00274761
    },
    "2025": {
      "adpe": 2.77883e-7,
      "ap": 0.0000583535,
      "ctue": 0.00864425,
      "ctuh-c": 4.56141e-10,
      "ctuh-nc": 9.33949e-10,
      "gwp": 0.00419249,
      "ir": 0.000523778,
      "pm": 0.00000141907,
      "wu": 0.00282542
    }
  },
  "Europe": {
    "2019": {
      "adpe": 2.33555e-7,
      "ap": 0.0000809574,
      "ctue": 0.013762,
      "ctuh-c": 7.16511e-10,
      "ctuh-nc": 1.18368e-9,
      "gwp": 0.0060792,
      "ir": 0.000552883,
      "pm": 0.00000211685,
      "wu": 0.00360448
    },
    "2020": {
      "adpe": 2.76541e-7,
      "ap": 0.0000875788,
      "ctue": 0.015573,
      "ctuh-c": 8.28919e-10,
      "ctuh-nc": 1.32579e-9,
      "gwp": 0.00671067,
      "ir": 0.000632647,
      "pm": 0.00000224451,
      "wu": 0.00399033
    },
    "2021": {
      "adpe": 2.85868e-7,
      "ap": 0.0000893063,
      "ctue": 0.0150693,
      "ctuh-c": 7.97809e-10,
      "ctuh-nc": 1.3314e-9,
      "gwp": 0.00667537,
      "ir": 0.000641138,
      "pm": 0.00000230714,
      "wu": 0.00404975
    },
    "2022": {
      "adpe": 3.48545e-7,
      "ap": 0.000092675,
      "ctue": 0.0164575,
      "ctuh-c": 9.04434e-10,
      "ctuh-nc": 1.45971e-9,
      "gwp": 0.00708013,
      "ir": 0.000733269,
      "pm": 0.00000231429,
      "wu": 0.00437591
    },
    "2023": {
      "adpe": 4.1035e-7,
      "ap": 0.0000923457,
      "ctue": 0.0184727,
      "ctuh-c": 1.0219e-9,
      "ctuh-nc": 1.58865e-9,
      "gwp": 0.00756549,
      "ir": 0.000837264,
      "pm": 0.00000215736,
      "wu": 0.00458368
    },
    "2024": {
      "adpe": 4.7608e-7,
      "ap": 0.0000977693,
      "ctue": 0.0196379,
      "ctuh-c": 1.06866e-9,
      "ctuh-nc": 1.73407e-9,
      "gwp": 0.00812123,
      "ir": 0.00094829,
      "pm": 0.00000221366,
      "wu": 0.00494246
    },
    "2025": {
      "adpe": 2.64145e-7,
      "ap": 0.0000838846,
      "ctue": 0.0172297,
      "ctuh-c": 1.05572e-9,
      "ctuh-nc": 1.31775e-9,
      "gwp": 0.00657366,
      "ir": 0.000588197,
      "pm": 0.00000215495,
      "wu": 0.00399205
    }
  },
  "North America": {
    "2019": {
      "adpe": 1.9296e-7,
      "ap": 0.0000691545,
      "ctue": 0.0101236,
      "ctuh-c": 5.3366e-10,
      "ctuh-nc": 9.50759e-10,
      "gwp": 0.00479322,
      "ir": 0.000439558,
      "pm": 0.00000187484,
      "wu": 0.0030181
    },
    "2020": {
      "adpe": 2.27359e-7,
      "ap": 0.0000708217,
      "ctue": 0.0112355,
      "ctuh-c": 6.07507e-10,
      "ctuh-nc": 1.03173e-9,
      "gwp": 0.00509761,
      "ir": 0.000495656,
      "pm": 0.00000185909,
      "wu": 0.00319985
    },
    "2021": {
      "adpe": 2.59418e-7,
      "ap": 0.0000713992,
      "ctue": 0.0118292,
      "ctuh-c": 6.54467e-10,
      "ctuh-nc": 1.08706e-9,
      "gwp": 0.00524436,
      "ir": 0.000540879,
      "pm": 0.00000182475,
      "wu": 0.0033249
    },
    "2022": {
      "adpe": 2.94624e-7,
      "ap": 0.0000712047,
      "ctue": 0.0127819,
      "ctuh-c": 7.18365e-10,
      "ctuh-nc": 1.153e-9,
      "gwp": 0.00545634,
      "ir": 0.000595076,
      "pm": 0.00000174561,
      "wu": 0.00344216
    },
    "2023": {
      "adpe": 3.31121e-7,
      "ap": 0.0000724879,
      "ctue": 0.0131548,
      "ctuh-c": 7.39028e-10,
      "ctuh-nc": 1.2131e-9,
      "gwp": 0.00562074,
      "ir": 0.000648725,
      "pm": 0.0000017292,
      "wu": 0.00358337
    },
    "2024": {
      "adpe": 3.82328e-7,
      "ap": 0.0000737721,
      "ctue": 0.0139439,
      "ctuh-c": 7.86164e-10,
      "ctuh-nc": 1.30202e-9,
      "gwp": 0.00588377,
      "ir": 0.000725721,
      "pm": 0.0000016814,
      "wu": 0.00377595
    },
    "2025": {
      "adpe": 3.16216e-7,
      "ap": 0.0000674176,
      "ctue": 0.0132517,
      "ctuh-c": 7.789e-10,
      "ctuh-nc": 1.16301e-9,
      "gwp": 0.00536512,
      "ir": 0.0006148,
      "pm": 0.00000158521,
      "wu": 0.00341118
    }
  },
  "Oceania": {
    "2019": {
      "adpe": 3.37275e-7,
      "ap": 0.0000366184,
      "ctue": 0.0120932,
      "ctuh-c": 5.5878e-10,
      "ctuh-nc": 9.93201e-10,
      "gwp": 0.00454316,
      "ir": 0.000658043,
      "pm": 4.01985e-7,
      "wu": 0.00231331
    },
    "2020": {
      "adpe": 4.05008e-7,
      "ap": 0.0000399158,
      "ctue": 0.0135162,
      "ctuh-c": 6.44979e-10,
      "ctuh-nc": 1.13174e-9,
      "gwp": 0.00501954,
      "ir": 0.000764772,
      "pm": 3.85775e-7,
      "wu": 0.00263443
    },
    "2021": {
      "adpe": 4.91636e-7,
      "ap": 0.0000447533,
      "ctue": 0.0153828,
      "ctuh-c": 7.51602e-10,
      "ctuh-nc": 1.3152e-9,
      "gwp": 0.00567645,
      "ir": 0.000904418,
      "pm": 3.8223e-7,
      "wu": 0.00306233
    },
    "2022": {
      "adpe": 5.64215e-7,
      "ap": 0.000048554,
      "ctue": 0.0169897,
      "ctuh-c": 8.40251e-10,
      "ctuh-nc": 1.46927e-9,
      "gwp": 0.00623632,
      "ir": 0.00102279,
      "pm": 3.67169e-7,
      "wu": 0.00341189
    },
    "2023": {
      "adpe": 6.72584e-7,
      "ap": 0.0000547714,
      "ctue": 0.0186304,
      "ctuh-c": 9.24271e-10,
      "ctuh-nc": 1.68001e-9,
      "gwp": 0.00694001,
      "ir": 0.00119276,
      "pm": 3.84047e-7,
      "wu": 0.00392187
    },
    "2024": {
      "adpe": 7.12792e-7,
      "ap": 0.0000571836,
      "ctue": 0.0189888,
      "ctuh-c": 9.55396e-10,
      "ctuh-nc": 1.74859e-9,
      "gwp": 0.0071118,
      "ir": 0.00124816,
      "pm": 4.09706e-7,
      "wu": 0.00411613
    },
    "2025": {
      "adpe": 8.81829e-7,
      "ap": 0.0000668275,
      "ctue": 0.0209906,
      "ctuh-c": 1.00969e-9,
      "ctuh-nc": 2.06766e-9,
      "gwp": 0.00820958,
      "ir": 0.00152194,
      "pm": 4.25315e-7,
      "wu": 0.00485869
    }
  },
  "South America": {
    "2019": {
      "adpe": 1.03872e-7,
      "ap": 0.0000473865,
      "ctue": 0.0201639,
      "ctuh-c": 4.54633e-10,
      "ctuh-nc": 1.14576e-9,
      "gwp": 0.00792037,
      "ir": 0.000643887,
      "pm": 5.47401e-7,
      "wu": 0.00197627
    },
    "2020": {
      "adpe": 1.21589e-7,
      "ap": 0.0000496188,
      "ctue": 0.0204933,
      "ctuh-c": 4.83127e-10,
      "ctuh-nc": 1.18741e-9,
      "gwp": 0.008058,
      "ir": 0.000669491,
      "pm": 5.98197e-7,
      "wu": 0.00210921
    },
    "2021": {
      "adpe": 1.47538e-7,
      "ap": 0.0000477463,
      "ctue": 0.0205701,
      "ctuh-c": 5.37882e-10,
      "ctuh-nc": 1.19869e-9,
      "gwp": 0.00790441,
      "ir": 0.00068616,
      "pm": 5.21506e-7,
      "wu": 0.0021492
    },
    "2022": {
      "adpe": 1.94401e-7,
      "ap": 0.0000509147,
      "ctue": 0.0221657,
      "ctuh-c": 6.00454e-10,
      "ctuh-nc": 1.32437e-9,
      "gwp": 0.00848205,
      "ir": 0.000778628,
      "pm": 5.05449e-7,
      "wu": 0.00239818
    },
    "2023": {
      "adpe": 2.53884e-7,
      "ap": 0.0000548357,
      "ctue": 0.0231601,
      "ctuh-c": 6.67134e-10,
      "ctuh-nc": 1.44332e-9,
      "gwp": 0.00886392,
      "ir": 0.00086826,
      "pm": 5.38711e-7,
      "wu": 0.00270866
    },
    "2024": {
      "adpe": 3.18457e-7,
      "ap": 0.0000587391,
      "ctue": 0.0239432,
      "ctuh-c": 7.31462e-10,
      "ctuh-nc": 1.55961e-9,
      "gwp": 0.00917881,
      "ir": 0.000958835,
      "pm": 5.76143e-7,
      "wu": 0.00303047
    },
    "2025": {
      "adpe": 3.64539e-7,
      "ap": 0.0000560831,
      "ctue": 0.0243072,
      "ctuh-c": 6.69037e-10,
      "ctuh-nc": 1.62105e-9,
      "gwp": 0.00944671,
      "ir": 0.00105,
      "pm": 3.58883e-7,
      "wu": 0.00300755
    }
  }
}