{
  "Africa": {
    "2019": {
      "Bioenergy": 0.023,
      "Hydro": 0.9203,
      "Solar": 0.0348,
      "Wind": 0.0218
    },
    "2020": {
      "Bioenergy": 0.023,
      "Hydro": 0.9222,
      "Solar": 0.0368,
      "Wind": 0.0179
    },
    "2021": {
      "Bioenergy": 0.023,
      "Hydro": 0.9185,
      "Solar": 0.0386,
      "Wind": 0.0199
    },
    "2022": {
      "Bioenergy": 0.0229,
      "Hydro": 0.9154,
      "Solar": 0.0408,
      "Wind": 0.0209
    },
    "2023": {
      "Bioenergy": 0.0227,
      "Hydro": 0.9099,
      "Solar": 0.0444,
      "Wind": 0.023
    },
    "2024": {
      "Bioenergy": 0.0225,
      "Hydro": 0.9061,
      "Solar": 0.0476,
      "Wind": 0.0237
    }
  },
  "Asia": {
    "2019": {
      "Bioenergy": 0.0763,
      "Hydro": 0.6903,
      "Solar": 0.1156,
      "Wind": 0.1178
    },
    "2020": {
      "Bioenergy": 0.0784,
      "Hydro": 0.6702,
      "Solar": 0.1258,
      "Wind": 0.1255
    },
    "2021": {
      "Bioenergy": 0.0784,
      "Hydro": 0.6224,
      "Solar": 0.1406,
      "Wind": 0.1586
    },
    "2022": {
      "Bioenergy": 0.0762,
      "Hydro": 0.5935,
      "Solar": 0.1597,
      "Wind": 0.1706
    },
    "2023": {
      "Bioenergy": 0.0792,
      "Hydro": 0.549,
      "Solar": 0.1873,
      "Wind": 0.1845
    },
    "2024": {
      "Bioenergy": 0.0917,
      "Hydro": 0.5061,
      "Solar": 0.1737,
      "Wind": 0.2286
    }
  },
  "Europe": {
    "2019": {
      "Bioenergy": 0.0755,
      "Hydro": 0.5922,
      "Solar": 0.0812,
      "Wind": 0.2511
    },
    "2020": {
      "Bioenergy": 0.0726,
      "Hydro": 0.5727,
      "Solar": 0.0899,
      "Wind": 0.2648
    },
    "2021": {
      "Bioenergy": 0.0777,
      "Hydro": 0.5634,
      "Solar": 0.0988,
      "Wind": 0.26
    },
    "2022": {
      "Bioenergy": 0.0758,
      "Hydro": 0.5183,
      "Solar": 0.1212,
      "Wind": 0.2848
    },
    "2023": {
      "Bioenergy": 0.0647,
      "Hydro": 0.5076,
      "Solar": 0.1335,
      "Wind": 0.2942
    },
    "2024": {
      "Bioenergy": 0.0633,
      "Hydro": 0.5185,
      "Solar": 0.0521,
      "Wind": 0.366
    }
  },
  "North America": {
    "2019": {
      "Bioenergy": 0.0958,
      "Hydro": 0.547,
      "Solar": 0.0997,
      "Wind": 0.2575
    },
    "2020": {
      "Bioenergy": 0.089,
      "Hydro": 0.522,
      "Solar": 0.1135,
      "Wind": 0.2755
    },
    "2021": {
      "Bioenergy": 0.086,
      "Hydro": 0.4917,
      "Solar": 0.1312,
      "Wind": 0.2911
    },
    "2022": {
      "Bioenergy": 0.0788,
      "Hydro": 0.47,
      "Solar": 0.146,
      "Wind": 0.3051
    },
    "2023": {
      "Bioenergy": 0.0761,
      "Hydro": 0.4462,
      "Solar": 0.1705,
      "Wind": 0.3071
    },
    "2024": {
      "Bioenergy": 0.0541,
      "Hydro": 0.4815,
      "Solar": 0.1349,
      "Wind": 0.3296
    }
  },
  "Oceania": {
    "2019": {
      "Bioenergy": 0.03,
      "Hydro": 0.5727,
      "Solar": 0.1969,
      "Wind": 0.2004
    },
    "2020": {
      "Bioenergy": 0.0275,
      "Hydro": 0.5325,
      "Solar": 0.2238,
      "Wind": 0.2162
    },
    "2021": {
      "Bioenergy": 0.0249,
      "Hydro": 0.4955,
      "Solar": 0.251,
      "Wind": 0.2286
    },
    "2022": {
      "Bioenergy": 0.0224,
      "Hydro": 0.4731,
      "Solar": 0.269,
      "Wind": 0.2355
    },
    "2023": {
      "Bioenergy": 0.0216,
      "Hydro": 0.436,
      "Solar": 0.3074,
      "Wind": 0.2351
    },
    "2024": {
      "Bioenergy": 0.0201,
      "Hydro": 0.3744,
      "Solar": 0.3813,
      "Wind": 0.2242
    }
  },
  "South America": {
    "2019": {
      "Bioenergy": 0.0121,
      "Hydro": 0.9204,
      "Solar": 0.0127,
      "Wind": 0.0548
    },
    "2020": {
      "Bioenergy": 0.0128,
      "Hydro": 0.9109,
      "Solar": 0.0171,
      "Wind": 0.0592
    },
    "2021": {
      "Bioenergy": 0.0115,
      "Hydro": 0.8882,
      "Solar": 0.0249,
      "Wind": 0.0754
    },
    "2022": {
      "Bioenergy": 0.0105,
      "Hydro": 0.8773,
      "Solar": 0.0335,
      "Wind": 0.0787
    },
    "2023": {
      "Bioenergy": 0.0109,
      "Hydro": 0.852,
      "Solar": 0.0504,
      "Wind": 0.0867
    },
    "2024": {
      "Bioenergy": 0.0075,
      "Hydro": 0.8602,
      "Solar": 0.0663,
      "Wind": 0.0659
    }
  }
}