{
  "2019": {
    "Bioenergy": 0.0633,
    "Hydro": 0.7112,
    "Solar": 0.0848,
    "Wind": 0.1406
  },
  "2020": {
    "Bioenergy": 0.0634,
    "Hydro": 0.6919,
    "Solar": 0.0943,
    "Wind": 0.1505
  },
  "2021": {
    "Bioenergy": 0.064,
    "Hydro": 0.6599,
    "Solar": 0.1073,
    "Wind": 0.1687
  },
  "2022": {
    "Bioenergy": 0.0616,
    "Hydro": 0.6341,
    "Solar": 0.1238,
    "Wind": 0.1805
  },
  "2023": {
    "Bioenergy": 0.0609,
    "Hydro": 0.6041,
    "Solar": 0.1441,
    "Wind": 0.1909
  },
  "2024": {
    "Bioenergy": 0.0649,
    "Hydro": 0.5839,
    "Solar": 0.1356,
    "Wind": 0.2156
  }
}